bizextract/__init__.py
bizextract/main.py
bizextract-0.2.0.dist-info/LICENSE
bizextract-0.2.0.dist-info/METADATA
bizextract-0.2.0.dist-info/WHEEL
bizextract-0.2.0.dist-info/entry_points.txt
bizextract-0.2.0.dist-info/top_level.txt
bizextract-0.2.0.dist-info/RECORD
