Metadata-Version: 2.1
Name: bizextract
Version: 0.2.0
Summary: Simple script for extracting business data from PDFs.
Author: Kevin Finnigin
License: MIT
Classifier: Programming Language :: Python :: 3
Classifier: License :: OSI Approved :: MIT License
Classifier: Operating System :: OS Independent
Requires-Python: >=3.10
License-File: LICENSE
Requires-Dist: tabulate
Requires-Dist: tika
